<?xml version='1.0' encoding='utf-8'?>
<annotation><folder>Unspecified</folder><filename>00116_0001_0001.jpg</filename><path>training_datasets/v2_generated/1_trvo/20210219-1108-56-538/00116_0001_0001.jpg</path><source><database>Unknown</database></source><size><width>624</width><height>281</height><depth>3</depth></size><segmented>0</segmented><object><name>0</name><pose>Unspecified</pose><truncated>0</truncated><difficult>0</difficult><bndbox><xmin>246.6200155234959</xmin><ymin>92.18150489133313</ymin><xmax>262.54411837782965</xmax><ymax>117.72478247508974</ymax></bndbox></object><object><name>0</name><pose>Unspecified</pose><truncated>0</truncated><difficult>0</difficult><bndbox><xmin>274.7125938550345</xmin><ymin>91.22964143957819</ymin><xmax>290.59931319036326</xmax><ymax>115.77361803138751</ymax></bndbox></object><object><name>5</name><pose>Unspecified</pose><truncated>0</truncated><difficult>0</difficult><bndbox><xmin>302.76778866756814</xmin><ymin>89.27847699587596</ymin><xmax>317.6925905299546</xmax><ymax>114.78437106062756</ymax></bndbox></object><object><name>2</name><pose>Unspecified</pose><truncated>0</truncated><difficult>0</difficult><bndbox><xmin>329.74891545014447</xmin><ymin>89.28853101706329</ymin><xmax>346.7097028154305</xmax><ymax>115.86849311177218</ymax></bndbox></object><object><name>3</name><pose>Unspecified</pose><truncated>0</truncated><difficult>0</difficult><bndbox><xmin>356.87957630874087</xmin><ymin>87.29998305435606</ymin><xmax>374.80228114696905</xmax><ymax>112.91802767612268</ymax></bndbox></object><object><name>5</name><pose>Unspecified</pose><truncated>0</truncated><difficult>0</difficult><bndbox><xmin>384.7852370452545</xmin><ymin>87.3474205945484</ymin><xmax>401.82079144855044</xmax><ymax>115.92598467315185</ymax></bndbox></object><object><name>4</name><pose>Unspecified</pose><truncated>0</truncated><difficult>0</difficult><bndbox><xmin>414.6894997656627</xmin><ymin>89.46822715664524</ymin><xmax>433.7610396718582</xmax><ymax>119.12085926520592</ymax></bndbox></object><object><name>screen</name><pose>Unspecified</pose><truncated>0</truncated><difficult>0</difficult><bndbox><xmin>214.93139791203572</xmin><ymin>63.0421880276549</ymin><xmax>467.448259267213</xmax><ymax>144.337739199105</ymax></bndbox></object></annotation>