<?xml version='1.0' encoding='utf-8'?>
<annotation><folder>Unspecified</folder><filename>00116_0002_0000.jpg</filename><path>training_datasets/v2_generated/1_trvo/20210219-1108-56-538/00116_0002_0000.jpg</path><source><database>Unknown</database></source><size><width>410</width><height>184</height><depth>3</depth></size><segmented>0</segmented><object><name>0</name><pose>Unspecified</pose><truncated>0</truncated><difficult>0</difficult><bndbox><xmin>65.54932290676732</xmin><ymin>87.15647660615559</ymin><xmax>82.50975517799651</xmax><ymax>113.2809935103204</ymax></bndbox></object><object><name>0</name><pose>Unspecified</pose><truncated>0</truncated><difficult>0</difficult><bndbox><xmin>93.29805833817386</xmin><ymin>82.91293068819925</ymin><xmax>110.17813297635735</xmax><ymax>108.04068149602483</ymax></bndbox></object><object><name>5</name><pose>Unspecified</pose><truncated>0</truncated><difficult>0</difficult><bndbox><xmin>120.96643613653475</xmin><ymin>77.75297630694928</ymin><xmax>136.93010231142472</xmax><ymax>103.79713557806843</ymax></bndbox></object><object><name>2</name><pose>Unspecified</pose><truncated>0</truncated><difficult>0</difficult><bndbox><xmin>147.79876310464772</xmin><ymin>74.42583885228646</ymin><xmax>165.83631910526168</xmax><ymax>101.62747948583615</ymax></bndbox></object><object><name>3</name><pose>Unspecified</pose><truncated>0</truncated><difficult>0</difficult><bndbox><xmin>174.47037480666944</xmin><ymin>69.18552683799089</ymin><xmax>193.42433927057687</xmax><ymax>95.470759008247</ymax></bndbox></object><object><name>5</name><pose>Unspecified</pose><truncated>0</truncated><difficult>0</difficult><bndbox><xmin>202.29946787112164</xmin><ymin>66.01910464941938</ymin><xmax>220.49773913782684</xmax><ymax>95.21427747564746</ymax></bndbox></object><object><name>4</name><pose>Unspecified</pose><truncated>0</truncated><difficult>0</difficult><bndbox><xmin>232.28280839434342</xmin><ymin>64.44442648829806</ymin><xmax>252.55496948677268</xmax><ymax>94.79708067695663</ymax></bndbox></object><object><name>screen</name><pose>Unspecified</pose><truncated>0</truncated><difficult>0</difficult><bndbox><xmin>32.39956019497396</xmin><ymin>42.85406876734697</ymin><xmax>287.37683385906195</xmax><ymax>134.71063596518024</ymax></bndbox></object></annotation>