<?xml version='1.0' encoding='utf-8'?>
<annotation><folder>Unspecified</folder><filename>00110_0014_0005.jpg</filename><path>training_datasets/v2_generated/1_trvo/20210219-1100-44-354/00110_0014_0005.jpg</path><source><database>Unknown</database></source><size><width>435</width><height>196</height><depth>3</depth></size><segmented>0</segmented><object><name>2</name><pose>Unspecified</pose><truncated>0</truncated><difficult>0</difficult><bndbox><xmin>66.84430845178815</xmin><ymin>48.814798495222874</ymin><xmax>81.39916490458472</xmax><ymax>70.18055639868982</ymax></bndbox></object><object><name>6</name><pose>Unspecified</pose><truncated>0</truncated><difficult>0</difficult><bndbox><xmin>92.88838525258558</xmin><ymin>50.147620861600615</ymin><xmax>106.41693843806041</xmax><ymax>70.4870754977457</ymax></bndbox></object><object><name>6</name><pose>Unspecified</pose><truncated>0</truncated><difficult>0</difficult><bndbox><xmin>118.87914470758562</xmin><ymin>49.45449536623346</ymin><xmax>132.38103922016154</xmax><ymax>68.7943054079555</ymax></bndbox></object><object><name>2</name><pose>Unspecified</pose><truncated>0</truncated><difficult>0</difficult><bndbox><xmin>145.8428900841099</xmin><ymin>47.7617252764432</ymin><xmax>158.39845734806033</xmax><ymax>69.07416583411265</ymax></bndbox></object><object><name>7</name><pose>Unspecified</pose><truncated>0</truncated><difficult>0</difficult><bndbox><xmin>170.8340049446868</xmin><ymin>47.068599781076045</ymin><xmax>184.38921680306038</xmax><ymax>68.40769901164418</ymax></bndbox></object><object><name>0</name><pose>Unspecified</pose><truncated>0</truncated><difficult>0</difficult><bndbox><xmin>198.824053588533</xmin><ymin>46.34881561281014</ymin><xmax>211.3796208524834</xmax><ymax>67.66125617047959</ymax></bndbox></object><object><name>screen</name><pose>Unspecified</pose><truncated>0</truncated><difficult>0</difficult><bndbox><xmin>47.371205045572424</xmin><ymin>26.715760169201985</ymin><xmax>235.8242885579159</xmax><ymax>88.68067388338125</ymax></bndbox></object></annotation>