<?xml version='1.0' encoding='utf-8'?>
<annotation><folder>Unspecified</folder><filename>00005_0014_0000.jpg</filename><path>training_datasets/v2_generated/1_trvo/20210219-1109-38-001/00005_0014_0000.jpg</path><source><database>Unknown</database></source><size><width>545</width><height>246</height><depth>3</depth></size><segmented>0</segmented><object><name>0</name><pose>Unspecified</pose><truncated>0</truncated><difficult>0</difficult><bndbox><xmin>215.2583904443419</xmin><ymin>47.38325073438784</ymin><xmax>230.64800051563577</xmax><ymax>69.77184996445965</ymax></bndbox></object><object><name>0</name><pose>Unspecified</pose><truncated>0</truncated><difficult>0</difficult><bndbox><xmin>235.8751134884078</xmin><ymin>43.034751705218184</ymin><xmax>250.2717248357875</xmax><ymax>65.30522585622293</ymax></bndbox></object><object><name>2</name><pose>Unspecified</pose><truncated>0</truncated><difficult>0</difficult><bndbox><xmin>255.61696288762653</xmin><ymin>39.44300124182871</ymin><xmax>272.1176967619018</xmax><ymax>62.942724274881755</ymax></bndbox></object><object><name>5</name><pose>Unspecified</pose><truncated>0</truncated><difficult>0</difficult><bndbox><xmin>275.4769373659123</xmin><ymin>37.198624739554646</ymin><xmax>291.10279759534023</xmax><ymax>61.57322141745499</ymax></bndbox></object><object><name>4</name><pose>Unspecified</pose><truncated>0</truncated><difficult>0</difficult><bndbox><xmin>296.21178548904527</xmin><ymin>33.96124951336634</ymin><xmax>309.6153981125105</xmax><ymax>56.11359858530392</ymax></bndbox></object><object><name>1</name><pose>Unspecified</pose><truncated>0</truncated><difficult>0</difficult><bndbox><xmin>316.071759967331</xmin><ymin>31.598747932025276</ymin><xmax>329.7116227489304</xmax><ymax>55.73709445179145</ymax></bndbox></object><object><name>6</name><pose>Unspecified</pose><truncated>0</truncated><difficult>0</difficult><bndbox><xmin>339.80773315851803</xmin><ymin>44.88797577517863</ymin><xmax>352.14822007038003</xmax><ymax>58.103336331887704</ymax></bndbox></object><object><name>screen</name><pose>Unspecified</pose><truncated>0</truncated><difficult>0</difficult><bndbox><xmin>190.5294185292405</xmin><ymin>13.422134054499907</ymin><xmax>384.5849316186617</xmax><ymax>89.36970508954465</ymax></bndbox></object></annotation>