<?xml version='1.0' encoding='utf-8'?>
<annotation><folder>Unspecified</folder><filename>000010_0008_0003.jpg</filename><path>../training_datasets/v1_generated/Musson_counters/000010_0008_0003.jpg</path><source><database>Unknown</database></source><size><width>442</width><height>199</height><depth>3</depth></size><segmented>0</segmented><object><name>0</name><pose>Unspecified</pose><truncated>0</truncated><difficult>0</difficult><bndbox><xmin>155.66849944631326</xmin><ymin>105.80564421949265</ymin><xmax>176.9006297061075</xmax><ymax>138.56090617646925</ymax></bndbox></object><object><name>2</name><pose>Unspecified</pose><truncated>0</truncated><difficult>0</difficult><bndbox><xmin>191.48522423908503</xmin><ymin>100.36645914073762</ymin><xmax>213.8335316862976</xmax><ymax>136.15842023466286</ymax></bndbox></object><object><name>6</name><pose>Unspecified</pose><truncated>0</truncated><difficult>0</difficult><bndbox><xmin>228.53506337876507</xmin><ymin>101.00067233587998</ymin><xmax>248.88489077012065</xmax><ymax>136.71467532347862</ymax></bndbox></object><object><name>0</name><pose>Unspecified</pose><truncated>0</truncated><difficult>0</difficult><bndbox><xmin>263.27459003728194</xmin><ymin>93.60198625443121</ymin><xmax>284.62365745656615</xmax><ymax>129.35496829519326</ymax></bndbox></object><object><name>9</name><pose>Unspecified</pose><truncated>0</truncated><difficult>0</difficult><bndbox><xmin>299.3641682021968</xmin><ymin>95.23543947750198</ymin><xmax>319.5970584340627</xmax><ymax>127.95172238131528</ymax></bndbox></object><object><name>6</name><pose>Unspecified</pose><truncated>0</truncated><difficult>0</difficult><bndbox><xmin>336.3360492355503</xmin><ymin>93.83219356362412</ymin><xmax>355.6086784926509</xmax><ymax>127.50873744220263</ymax></bndbox></object><object><name>6</name><pose>Unspecified</pose><truncated>0</truncated><difficult>0</difficult><bndbox><xmin>372.91813973727113</xmin><ymin>82.35858926413488</ymin><xmax>392.9561347033204</xmax><ymax>110.0786720283059</ymax></bndbox></object><object><name>7</name><pose>Unspecified</pose><truncated>0</truncated><difficult>0</difficult><bndbox><xmin>375.0477723069345</xmin><ymin>111.33655007406065</ymin><xmax>393.8526529260758</xmax><ymax>133.02221361749747</ymax></bndbox></object><object><name>screen</name><pose>Unspecified</pose><truncated>0</truncated><difficult>0</difficult><bndbox><xmin>120.56394595501024</xmin><ymin>67.04394106558505</ymin><xmax>428.48945777941964</xmax><ymax>159.87099454259004</ymax></bndbox></object></annotation>