<?xml version='1.0' encoding='utf-8'?>
<annotation><folder>Unspecified</folder><filename>000017_0003_0003.jpg</filename><path>../training_datasets/v1_generated/Musson_counters/000017_0003_0003.jpg</path><source><database>Unknown</database></source><size><width>428</width><height>193</height><depth>3</depth></size><segmented>0</segmented><object><name>0</name><pose>Unspecified</pose><truncated>0</truncated><difficult>0</difficult><bndbox><xmin>87.27842518801032</xmin><ymin>105.51833896854669</ymin><xmax>108.43754374904688</xmax><ymax>142.6084170055783</ymax></bndbox></object><object><name>3</name><pose>Unspecified</pose><truncated>0</truncated><difficult>0</difficult><bndbox><xmin>125.26084988244634</xmin><ymin>101.36336858313905</ymin><xmax>144.41137545734244</xmax><ymax>136.44485363403032</ymax></bndbox></object><object><name>3</name><pose>Unspecified</pose><truncated>0</truncated><difficult>0</difficult><bndbox><xmin>161.25621040529302</xmin><ymin>100.21267615112129</ymin><xmax>179.4067452500293</xmax><ymax>135.28985543910233</ymax></bndbox></object><object><name>6</name><pose>Unspecified</pose><truncated>0</truncated><difficult>0</difficult><bndbox><xmin>195.26881251946077</xmin><ymin>103.05764087683292</ymin><xmax>215.41932882451692</xmax><ymax>138.14343169063443</ymax></bndbox></object><object><name>5</name><pose>Unspecified</pose><truncated>0</truncated><difficult>0</difficult><bndbox><xmin>231.24694999066662</xmin><ymin>97.89406823544482</ymin><xmax>253.4017535189529</xmax><ymax>133.9884613052268</ymax></bndbox></object><object><name>7</name><pose>Unspecified</pose><truncated>0</truncated><difficult>0</difficult><bndbox><xmin>268.2552185324039</xmin><ymin>99.75195951972728</ymin><xmax>286.4100591400504</xmax><ymax>135.8291295378683</ymax></bndbox></object><object><name>4</name><pose>Unspecified</pose><truncated>0</truncated><difficult>0</difficult><bndbox><xmin>308.2333189242495</xmin><ymin>94.57546958960859</ymin><xmax>327.3623156845946</xmax><ymax>124.65700098970024</ymax></bndbox></object><object><name>screen</name><pose>Unspecified</pose><truncated>0</truncated><difficult>0</difficult><bndbox><xmin>49.18405065790864</xmin><ymin>82.42487912583181</ymin><xmax>362.5342217566006</xmax><ymax>165.7718227898448</ymax></bndbox></object></annotation>