<?xml version='1.0' encoding='utf-8'?>
<annotation><folder>Unspecified</folder><filename>000022_0007_0003.jpg</filename><path>../training_datasets/v1_generated/Musson_counters/000022_0007_0003.jpg</path><source><database>Unknown</database></source><size><width>541</width><height>243</height><depth>3</depth></size><segmented>0</segmented><object><name>0</name><pose>Unspecified</pose><truncated>0</truncated><difficult>0</difficult><bndbox><xmin>224.80200972907033</xmin><ymin>162.53935516431352</ymin><xmax>246.57894751454006</xmax><ymax>186.2464794773083</ymax></bndbox></object><object><name>0</name><pose>Unspecified</pose><truncated>0</truncated><difficult>0</difficult><bndbox><xmin>261.6772626332733</xmin><ymin>161.81028849192433</ymin><xmax>281.626967021658</xmax><ymax>190.44583225417182</ymax></bndbox></object><object><name>5</name><pose>Unspecified</pose><truncated>0</truncated><difficult>0</difficult><bndbox><xmin>296.6566467200979</xmin><ymin>163.01140834706</ymin><xmax>315.6069401345734</xmax><ymax>191.6126343991608</ymax></bndbox></object><object><name>9</name><pose>Unspecified</pose><truncated>0</truncated><difficult>0</difficult><bndbox><xmin>329.60289114895727</xmin><ymin>163.14448180799297</ymin><xmax>351.62005290545403</xmax><ymax>193.84748293835253</ymax></bndbox></object><object><name>2</name><pose>Unspecified</pose><truncated>0</truncated><difficult>0</difficult><bndbox><xmin>365.6160039198378</xmin><ymin>160.38227547763825</ymin><xmax>385.73729685895637</xmax><ymax>194.0148741094323</ymax></bndbox></object><object><name>9</name><pose>Unspecified</pose><truncated>0</truncated><difficult>0</difficult><bndbox><xmin>401.5947989805717</xmin><ymin>162.61712401683008</ymin><xmax>421.6817742095435</xmax><ymax>195.2503116747148</ymax></bndbox></object><object><name>0</name><pose>Unspecified</pose><truncated>0</truncated><difficult>0</difficult><bndbox><xmin>438.1913128239469</xmin><ymin>154.85786281692907</ymin><xmax>457.96942866159793</xmax><ymax>178.4963517096303</ymax></bndbox></object><object><name>9</name><pose>Unspecified</pose><truncated>0</truncated><difficult>0</difficult><bndbox><xmin>230.65700735228506</xmin><ymin>142.72272423686178</ymin><xmax>249.2641236652933</xmax><ymax>161.32984054986997</ymax></bndbox></object><object><name>screen</name><pose>Unspecified</pose><truncated>0</truncated><difficult>0</difficult><bndbox><xmin>195.9948774160889</xmin><ymin>129.59730811510826</ymin><xmax>493.53221382091715</xmax><ymax>218.6744995472277</ymax></bndbox></object></annotation>