<?xml version='1.0' encoding='utf-8'?>
<annotation><folder>Unspecified</folder><filename>20200724_095628_0002_0003.jpg</filename><path>../training_datasets/v1_generated/Musson_counters_3/20200724_095628_0002_0003.jpg</path><source><database>Unknown</database></source><size><width>897</width><height>404</height><depth>3</depth></size><segmented>0</segmented><object><name>0</name><pose>Unspecified</pose><truncated>0</truncated><difficult>0</difficult><bndbox><xmin>545.4770815148572</xmin><ymin>185.30454517369537</ymin><xmax>568.2707255747114</xmax><ymax>218.8767910750371</ymax></bndbox></object><object><name>0</name><pose>Unspecified</pose><truncated>0</truncated><difficult>0</difficult><bndbox><xmin>581.7298460673484</xmin><ymin>186.90569137481793</ymin><xmax>602.5492736579257</xmax><ymax>219.37764408879264</ymax></bndbox></object><object><name>8</name><pose>Unspecified</pose><truncated>0</truncated><difficult>0</difficult><bndbox><xmin>617.0981653345048</xmin><ymin>190.03882898496113</ymin><xmax>637.018524303713</xmax><ymax>223.0682892195207</ymax></bndbox></object><object><name>2</name><pose>Unspecified</pose><truncated>0</truncated><difficult>0</difficult><bndbox><xmin>650.6432860316987</xmin><ymin>192.07174392142645</ymin><xmax>673.1456316656091</xmax><ymax>225.9352882487119</ymax></bndbox></object><object><name>3</name><pose>Unspecified</pose><truncated>0</truncated><difficult>0</difficult><bndbox><xmin>687.1622316747521</xmin><ymin>194.64737884616216</ymin><xmax>707.0322294513518</xmax><ymax>227.0438810362258</ymax></bndbox></object><object><name>3</name><pose>Unspecified</pose><truncated>0</truncated><difficult>0</difficult><bndbox><xmin>722.6814727410435</xmin><ymin>196.19822711559925</ymin><xmax>741.6272845608927</xmax><ymax>228.83579306084425</ymax></bndbox></object><object><name>2</name><pose>Unspecified</pose><truncated>0</truncated><difficult>0</difficult><bndbox><xmin>758.9342068718673</xmin><ymin>196.8499715068225</ymin><xmax>778.512971901035</xmax><ymax>229.53783780134154</ymax></bndbox></object><object><name>screen</name><pose>Unspecified</pose><truncated>0</truncated><difficult>0</difficult><bndbox><xmin>511.95930055632255</xmin><ymin>160.66239784331663</ymin><xmax>818.1378058458263</xmax><ymax>266.1258701403964</ymax></bndbox></object></annotation>