<?xml version='1.0' encoding='utf-8'?>
<annotation><folder>Unspecified</folder><filename>20200724_095714_0000_0002.jpg</filename><path>../training_datasets/v1_generated/Musson_counters_3/20200724_095714_0000_0002.jpg</path><source><database>Unknown</database></source><size><width>943</width><height>424</height><depth>3</depth></size><segmented>0</segmented><object><name>0</name><pose>Unspecified</pose><truncated>0</truncated><difficult>0</difficult><bndbox><xmin>370.9022843556079</xmin><ymin>78.8562518291368</ymin><xmax>398.04692916989404</xmax><ymax>125.54454382296433</ymax></bndbox></object><object><name>0</name><pose>Unspecified</pose><truncated>0</truncated><difficult>0</difficult><bndbox><xmin>419.6379135449919</xmin><ymin>79.31166265178297</ymin><xmax>449.4038415544561</xmax><ymax>124.4333383672348</ymax></bndbox></object><object><name>0</name><pose>Unspecified</pose><truncated>0</truncated><difficult>0</difficult><bndbox><xmin>471.22742900720505</xmin><ymin>83.6345017785062</ymin><xmax>499.73186166018775</xmax><ymax>128.611405230689</ymax></bndbox></object><object><name>2</name><pose>Unspecified</pose><truncated>0</truncated><difficult>0</difficult><bndbox><xmin>519.6527677700916</xmin><ymin>89.2085261867636</ymin><xmax>547.9865451689353</xmax><ymax>135.41078560789845</ymax></bndbox></object><object><name>4</name><pose>Unspecified</pose><truncated>0</truncated><difficult>0</difficult><bndbox><xmin>569.5413364782158</xmin><ymin>89.17790443671709</ymin><xmax>597.5235469721221</xmax><ymax>135.0285969529142</ymax></bndbox></object><object><name>2</name><pose>Unspecified</pose><truncated>0</truncated><difficult>0</difficult><bndbox><xmin>618.2096629485884</xmin><ymin>96.3650517435484</ymin><xmax>647.8049963410681</xmax><ymax>142.71209038681866</ymax></bndbox></object><object><name>7</name><pose>Unspecified</pose><truncated>0</truncated><difficult>0</difficult><bndbox><xmin>671.2881948166289</xmin><ymin>136.68891229914504</ymin><xmax>696.8814770698418</xmax><ymax>161.72383300575154</ymax></bndbox></object><object><name>6</name><pose>Unspecified</pose><truncated>0</truncated><difficult>0</difficult><bndbox><xmin>674.5922478526132</xmin><ymin>94.70586937104724</ymin><xmax>702.010832860145</xmax><ymax>130.2210725523836</ymax></bndbox></object><object><name>screen</name><pose>Unspecified</pose><truncated>0</truncated><difficult>0</difficult><bndbox><xmin>316.3136071520978</xmin><ymin>31.74896336250265</ymin><xmax>758.8639624141273</xmax><ymax>202.36312803762314</ymax></bndbox></object></annotation>