<?xml version='1.0' encoding='utf-8'?>
<annotation><folder>Unspecified</folder><filename>00031_0009_0004.jpg</filename><path>training_datasets/v2_generated/1_trvo/20210219-1054-39-265/00031_0009_0004.jpg</path><source><database>Unknown</database></source><size><width>243</width><height>110</height><depth>3</depth></size><segmented>0</segmented><object><name>1</name><pose>Unspecified</pose><truncated>0</truncated><difficult>0</difficult><bndbox><xmin>46.129141870820945</xmin><ymin>63.64489141768598</ymin><xmax>58.749517157048786</xmax><ymax>83.03048873336036</ymax></bndbox></object><object><name>5</name><pose>Unspecified</pose><truncated>0</truncated><difficult>0</difficult><bndbox><xmin>71.11552960850281</xmin><ymin>62.820010928027386</ymin><xmax>83.76890011431698</xmax><ymax>83.20506375320912</ymax></bndbox></object><object><name>8</name><pose>Unspecified</pose><truncated>0</truncated><difficult>0</difficult><bndbox><xmin>96.06892212659835</xmin><ymin>60.99567492886155</ymin><xmax>108.7552878519989</xmax><ymax>82.38018326355046</ymax></bndbox></object><object><name>8</name><pose>Unspecified</pose><truncated>0</truncated><difficult>0</difficult><bndbox><xmin>121.05530986428028</xmin><ymin>60.17079443920295</ymin><xmax>133.74167558968077</xmax><ymax>81.55530277389187</ymax></bndbox></object><object><name>2</name><pose>Unspecified</pose><truncated>0</truncated><difficult>0</difficult><bndbox><xmin>145.00924687286852</xmin><ymin>58.37945365962338</ymin><xmax>157.6296221590964</xmax><ymax>77.76505097529775</ymax></bndbox></object><object><name>7</name><pose>Unspecified</pose><truncated>0</truncated><difficult>0</difficult><bndbox><xmin>170.22660114765483</xmin><ymin>64.58375695610209</ymin><xmax>181.68254482644375</xmax><ymax>78.93908150465376</ymax></bndbox></object><object><name>screen</name><pose>Unspecified</pose><truncated>0</truncated><difficult>0</difficult><bndbox><xmin>30.60938571483024</xmin><ymin>42.770310766790715</ymin><xmax>207.03187997957536</xmax><ymax>94.51942763173554</ymax></bndbox></object></annotation>