<?xml version='1.0' encoding='utf-8'?>
<annotation><folder>Unspecified</folder><filename>00145_0005_0005.jpg</filename><path>training_datasets/v2_generated/1_trvo/20210219-1106-05-116/00145_0005_0005.jpg</path><source><database>Unknown</database></source><size><width>691</width><height>311</height><depth>3</depth></size><segmented>0</segmented><object><name>0</name><pose>Unspecified</pose><truncated>0</truncated><difficult>0</difficult><bndbox><xmin>101.61886555544879</xmin><ymin>133.00695266783228</ymin><xmax>118.02976888298258</xmax><ymax>161.17430098862297</ymax></bndbox></object><object><name>1</name><pose>Unspecified</pose><truncated>0</truncated><difficult>0</difficult><bndbox><xmin>128.50568632101817</xmin><ymin>130.53736381133447</ymin><xmax>145.0080559024965</xmax><ymax>159.70052030862774</ymax></bndbox></object><object><name>1</name><pose>Unspecified</pose><truncated>0</truncated><difficult>0</difficult><bndbox><xmin>156.47978151703478</xmin><ymin>129.06358313133924</ymin><xmax>171.9863429220103</xmax><ymax>158.1352733746881</ymax></bndbox></object><object><name>7</name><pose>Unspecified</pose><truncated>0</truncated><difficult>0</difficult><bndbox><xmin>183.6410010444373</xmin><ymin>129.4899525504048</ymin><xmax>199.86897186408248</xmax><ymax>155.6656845181903</ymax></bndbox></object><object><name>4</name><pose>Unspecified</pose><truncated>0</truncated><difficult>0</difficult><bndbox><xmin>211.7065624943981</xmin><ymin>128.92051379296777</ymin><xmax>227.93453331404328</xmax><ymax>155.09624576075328</ymax></bndbox></object><object><name>3</name><pose>Unspecified</pose><truncated>0</truncated><difficult>0</difficult><bndbox><xmin>237.50610882952083</xmin><ymin>125.54658301391171</ymin><xmax>253.91701215705473</xmax><ymax>153.7139313347024</ymax></bndbox></object><object><name>3</name><pose>Unspecified</pose><truncated>0</truncated><difficult>0</difficult><bndbox><xmin>267.2992084875391</xmin><ymin>132.7606771606066</ymin><xmax>284.1571224679094</xmax><ymax>155.04464267632613</ymax></bndbox></object><object><name>screen</name><pose>Unspecified</pose><truncated>0</truncated><difficult>0</difficult><bndbox><xmin>87.39283170569416</xmin><ymin>100.86385366186792</ymin><xmax>318.2993198477154</xmax><ymax>185.26695034945897</ymax></bndbox></object></annotation>