<?xml version='1.0' encoding='utf-8'?>
<annotation><folder>Unspecified</folder><filename>00072_0002_0000.jpg</filename><path>training_datasets/v2_generated/1_trvo/20210219-1056-36-143/00072_0002_0000.jpg</path><source><database>Unknown</database></source><size><width>711</width><height>320</height><depth>3</depth></size><segmented>0</segmented><object><name>0</name><pose>Unspecified</pose><truncated>0</truncated><difficult>0</difficult><bndbox><xmin>301.355973233308</xmin><ymin>52.270118591898495</ymin><xmax>324.73075317467135</xmax><ymax>84.40535162547565</ymax></bndbox></object><object><name>6</name><pose>Unspecified</pose><truncated>0</truncated><difficult>0</difficult><bndbox><xmin>335.23922537668994</xmin><ymin>55.25762996225478</ymin><xmax>360.60025088677344</xmax><ymax>87.62701794610928</ymax></bndbox></object><object><name>9</name><pose>Unspecified</pose><truncated>0</truncated><difficult>0</difficult><bndbox><xmin>371.98476839801333</xmin><ymin>60.58261932674736</ymin><xmax>393.2562252955178</xmax><ymax>91.49057462568692</ymax></bndbox></object><object><name>6</name><pose>Unspecified</pose><truncated>0</truncated><difficult>0</difficult><bndbox><xmin>406.978220800894</xmin><ymin>63.68720817224232</ymin><xmax>429.1257230076198</xmax><ymax>93.71911816196052</ymax></bndbox></object><object><name>0</name><pose>Unspecified</pose><truncated>0</truncated><difficult>0</difficult><bndbox><xmin>441.7375182534972</xmin><ymin>65.79867423337714</ymin><xmax>464.1191754105005</xmax><ymax>97.81682979181562</ymax></bndbox></object><object><name>7</name><pose>Unspecified</pose><truncated>0</truncated><difficult>0</difficult><bndbox><xmin>476.37973823096183</xmin><ymin>70.88950864759238</ymin><xmax>496.7751498192448</xmax><ymax>102.67350925575329</ymax></bndbox></object><object><name>4</name><pose>Unspecified</pose><truncated>0</truncated><difficult>0</difficult><bndbox><xmin>506.6376601536814</xmin><ymin>89.53282961743264</ymin><xmax>528.7851623604072</xmax><ymax>119.56473960715073</ymax></bndbox></object><object><name>screen</name><pose>Unspecified</pose><truncated>0</truncated><difficult>0</difficult><bndbox><xmin>273.6574697290882</xmin><ymin>22.645944010846847</ymin><xmax>567.234436034199</xmax><ymax>145.3940750177892</ymax></bndbox></object></annotation>