<?xml version='1.0' encoding='utf-8'?>
<annotation><folder>Unspecified</folder><filename>00019_0000_0002.jpg</filename><path>training_datasets/v2_generated/1_trvo/20210219-1106-35-973/00019_0000_0002.jpg</path><source><database>Unknown</database></source><size><width>808</width><height>363</height><depth>3</depth></size><segmented>0</segmented><object><name>0</name><pose>Unspecified</pose><truncated>0</truncated><difficult>0</difficult><bndbox><xmin>241.86369669063728</xmin><ymin>214.9120434857955</ymin><xmax>263.0971163868055</xmax><ymax>250.60191087908692</ymax></bndbox></object><object><name>4</name><pose>Unspecified</pose><truncated>0</truncated><difficult>0</difficult><bndbox><xmin>283.0157176191409</xmin><ymin>209.3761977253223</ymin><xmax>303.32097697368283</xmax><ymax>247.02919431641197</ymax></bndbox></object><object><name>2</name><pose>Unspecified</pose><truncated>0</truncated><difficult>0</difficult><bndbox><xmin>322.9191526623813</xmin><ymin>213.7984093065682</ymin><xmax>344.1881751967313</xmax><ymax>250.48764271784972</ymax></bndbox></object><object><name>3</name><pose>Unspecified</pose><truncated>0</truncated><difficult>0</difficult><bndbox><xmin>363.9643650763393</xmin><ymin>211.2606616000653</ymin><xmax>384.30522726906304</xmax><ymax>249.91302420914508</ymax></bndbox></object><object><name>3</name><pose>Unspecified</pose><truncated>0</truncated><difficult>0</difficult><bndbox><xmin>402.0114794363269</xmin><ymin>212.61356945097714</ymin><xmax>423.28050197067705</xmax><ymax>249.3028028622586</ymax></bndbox></object><object><name>6</name><pose>Unspecified</pose><truncated>0</truncated><difficult>0</difficult><bndbox><xmin>440.91554846157715</xmin><ymin>217.00017819404115</ymin><xmax>464.14770019372565</xmax><ymax>252.7612512636963</ymax></bndbox></object><object><name>2</name><pose>Unspecified</pose><truncated>0</truncated><difficult>0</difficult><bndbox><xmin>486.3167398782117</xmin><ymin>248.61888929011116</ymin><xmax>506.0523538218433</xmax><ymax>270.2820295933593</ymax></bndbox></object><object><name>1</name><pose>Unspecified</pose><truncated>0</truncated><difficult>0</difficult><bndbox><xmin>490.24051172491113</xmin><ymin>214.74725319299336</ymin><xmax>504.26475226605726</xmax><ymax>244.19170461107092</ymax></bndbox></object><object><name>screen</name><pose>Unspecified</pose><truncated>0</truncated><difficult>0</difficult><bndbox><xmin>202.712894347011</xmin><ymin>188.57498518513114</ymin><xmax>557.800796630443</xmax><ymax>294.048223898236</ymax></bndbox></object></annotation>