<?xml version='1.0' encoding='utf-8'?>
<annotation><folder>Unspecified</folder><filename>00142_0014_0003.jpg</filename><path>training_datasets/v2_generated/1_trvo/20210219-1109-55-309/00142_0014_0003.jpg</path><source><database>Unknown</database></source><size><width>876</width><height>395</height><depth>3</depth></size><segmented>0</segmented><object><name>1</name><pose>Unspecified</pose><truncated>0</truncated><difficult>0</difficult><bndbox><xmin>363.47925277409286</xmin><ymin>206.06217492353784</ymin><xmax>389.4580435586677</xmax><ymax>248.18816289595986</ymax></bndbox></object><object><name>0</name><pose>Unspecified</pose><truncated>0</truncated><difficult>0</difficult><bndbox><xmin>409.4240747558278</xmin><ymin>203.80976886185965</ymin><xmax>435.35390019123577</xmax><ymax>244.9369563564178</ymax></bndbox></object><object><name>8</name><pose>Unspecified</pose><truncated>0</truncated><difficult>0</difficult><bndbox><xmin>453.46922648016897</xmin><ymin>203.60392910507602</ymin><xmax>480.44681774260766</xmax><ymax>245.7788824266649</ymax></bndbox></object><object><name>5</name><pose>Unspecified</pose><truncated>0</truncated><difficult>0</difficult><bndbox><xmin>500.3638835906008</xmin><ymin>200.40168791470091</ymin><xmax>525.1969778498112</xmax><ymax>239.48230910436462</ymax></bndbox></object><object><name>8</name><pose>Unspecified</pose><truncated>0</truncated><difficult>0</difficult><bndbox><xmin>545.3588704436389</xmin><ymin>199.29497837838727</ymin><xmax>568.3412597946224</xmax><ymax>241.27407030330846</ymax></bndbox></object><object><name>7</name><pose>Unspecified</pose><truncated>0</truncated><difficult>0</difficult><bndbox><xmin>589.3060914696463</xmin><ymin>197.04257231670908</ymin><xmax>614.2860817763573</xmax><ymax>239.1195949399641</ymax></bndbox></object><object><name>5</name><pose>Unspecified</pose><truncated>0</truncated><difficult>0</difficult><bndbox><xmin>638.1983495358057</xmin><ymin>193.5955043804994</ymin><xmax>664.1281749712136</xmax><ymax>234.72269187505754</ymax></bndbox></object><object><name>screen</name><pose>Unspecified</pose><truncated>0</truncated><difficult>0</difficult><bndbox><xmin>307.3210927624107</xmin><ymin>164.4929096093578</ymin><xmax>730.6465690603437</xmax><ymax>303.817682426922</ymax></bndbox></object></annotation>