<?xml version='1.0' encoding='utf-8'?>
<annotation><folder>Unspecified</folder><filename>00142_0001_0004.jpg</filename><path>training_datasets/v2_generated/1_trvo/20210219-1109-55-309/00142_0001_0004.jpg</path><source><database>Unknown</database></source><size><width>1182</width><height>532</height><depth>3</depth></size><segmented>0</segmented><object><name>1</name><pose>Unspecified</pose><truncated>0</truncated><difficult>0</difficult><bndbox><xmin>117.86291586688105</xmin><ymin>79.06875704654283</ymin><xmax>146.6150706268237</xmax><ymax>122.65527618630125</ymax></bndbox></object><object><name>0</name><pose>Unspecified</pose><truncated>0</truncated><difficult>0</difficult><bndbox><xmin>163.6498462998324</xmin><ymin>84.59549618406174</ymin><xmax>192.28185455678545</xmax><ymax>127.18925915142967</ymax></bndbox></object><object><name>8</name><pose>Unspecified</pose><truncated>0</truncated><difficult>0</difficult><bndbox><xmin>206.97067837604465</xmin><ymin>91.86745466038252</ymin><xmax>236.71558930837767</xmax><ymax>135.57412030313043</ymax></bndbox></object><object><name>5</name><pose>Unspecified</pose><truncated>0</truncated><difficult>0</difficult><bndbox><xmin>254.11080449035506</xmin><ymin>96.52158412850048</ymin><xmax>281.5097635689386</xmax><ymax>137.00968824809792</ymax></bndbox></object><object><name>8</name><pose>Unspecified</pose><truncated>0</truncated><difficult>0</difficult><bndbox><xmin>298.30424623596826</xmin><ymin>102.92093293542035</ymin><xmax>324.07813247873946</xmax><ymax>146.14701256621015</ymax></bndbox></object><object><name>7</name><pose>Unspecified</pose><truncated>0</truncated><difficult>0</difficult><bndbox><xmin>341.98551782114913</xmin><ymin>108.20737906696019</ymin><xmax>369.7449164087011</xmax><ymax>151.67375170372907</ymax></bndbox></object><object><name>5</name><pose>Unspecified</pose><truncated>0</truncated><difficult>0</difficult><bndbox><xmin>390.8708632742614</xmin><ymin>113.10180154105723</ymin><xmax>419.5028715312144</xmax><ymax>155.6955645084252</ymax></bndbox></object><object><name>screen</name><pose>Unspecified</pose><truncated>0</truncated><difficult>0</difficult><bndbox><xmin>56.89356172695929</xmin><ymin>47.64179507235622</ymin><xmax>486.1630756419328</xmax><ymax>216.001017836451</ymax></bndbox></object></annotation>